datadog_lambda/__init__.py
datadog_lambda/api.py
datadog_lambda/cold_start.py
datadog_lambda/constants.py
datadog_lambda/dogstatsd.py
datadog_lambda/extension.py
datadog_lambda/handler.py
datadog_lambda/metric.py
datadog_lambda/module_name.py
datadog_lambda/patch.py
datadog_lambda/stats_writer.py
datadog_lambda/statsd_writer.py
datadog_lambda/tag_object.py
datadog_lambda/tags.py
datadog_lambda/thread_stats_writer.py
datadog_lambda/tracing.py
datadog_lambda/trigger.py
datadog_lambda/wrapper.py
datadog_lambda/xray.py
ivan_datadog_lambda-1.0.0.dist-info/LICENSE
ivan_datadog_lambda-1.0.0.dist-info/WHEEL
ivan_datadog_lambda-1.0.0.dist-info/METADATA
ivan_datadog_lambda-1.0.0.dist-info/RECORD
