Metadata-Version: 2.1
Name: ivan-datadog-lambda
Version: 1.0.0
Summary: The Datadog AWS Lambda Library
Home-page: https://github.com/DataDog/datadog-lambda-python
License: Apache-2.0
Keywords: datadog,aws,lambda,layer
Author: Datadog, Inc.
Author-email: dev@datadoghq.com
Requires-Python: >=3.7.0,<4
Classifier: License :: OSI Approved :: Apache Software License
Classifier: Programming Language :: Python :: 3
Classifier: Programming Language :: Python :: 3.7
Classifier: Programming Language :: Python :: 3.8
Classifier: Programming Language :: Python :: 3.9
Classifier: Programming Language :: Python :: 3.10
Classifier: Programming Language :: Python :: 3.11
Classifier: Programming Language :: Python :: 3.7
Classifier: Programming Language :: Python :: 3.8
Classifier: Programming Language :: Python :: 3.9
Provides-Extra: dev
Requires-Dist: boto3 (>=1.10.33,<2.0.0); extra == "dev"
Requires-Dist: datadog (>=0.41,<0.42)
Requires-Dist: ddtrace (>=1.4.1,<2.0.0)
Requires-Dist: flake8 (>=3.7.9,<4.0.0); extra == "dev"
Requires-Dist: httpretty (>=0.9.7,<0.10.0); extra == "dev"
Requires-Dist: importlib_metadata (>=1.0,<2.0); python_version < "3.8"
Requires-Dist: nose2 (>=0.9.1,<0.10.0); extra == "dev"
Requires-Dist: requests (>=2.22.0,<3.0.0); extra == "dev"
Requires-Dist: typing_extensions (>=4.0,<5.0); python_version < "3.8"
Requires-Dist: wrapt (>=1.11.2,<2.0.0)
Project-URL: Repository, https://github.com/DataDog/datadog-lambda-python
